{
    "products": [
        {
            "product_id": "R001",
            "name": "Rado HyperChrome Automatic",
            "watch_type": "Automatic",
            "price": 2200.00,
            "discount": 0,
            "gender": "men",
            "company": "Rado",
            "rating": "4.5",
            "numRatings": "2500",
            "isNew": true,
            "image_url": "./img/menwatch/top1.png",
            "sideImg_url": "./img/menwatch/top1-1.png",
            "images": [
                "./img/topSellSlide/top1.png",
                "./img/menwatch/1.png",
                "./img/menwatch/1_side.png"
            ],
            "topShow": true,
            "description": "A sophisticated automatic watch with a sleek design, perfect for any occasion."
        },
        {
            "product_id": "R002",
            "name": "Rado Centrix Quartz",
            "watch_type": "Quartz",
            "price": 1200.00,
            "discount": 10,
            "gender": "men",
            "company": "Rado",
            "rating": "4.2",
            "numRatings": "1500",
            "isNew": false,
            "image_url": "./img/menwatch/top2.png",
            "sideImg_url": "./img/menwatch/top2-1.png",
            "images": [
                "./img/topSellSlide/top2.png",
                "./img/menwatch/2.png",
                "./img/menwatch/2_side.png"
            ],
            "topShow": true,
            "description": "A classic quartz watch with a refined look, offering reliable timekeeping."
        },
        {
            "product_id": "R003",
            "name": "Rado Captain Cook Diver",
            "watch_type": "Diver",
            "price": 2500.00,
            "discount": 20,
            "gender": "men",
            "company": "Rado",
            "rating": "4.7",
            "numRatings": "800",
            "isNew": true,
            "image_url": "./img/menwatch/top3.png",
            "sideImg_url": "./img/menwatch/top3-1.png",
            "images": [
                "./img/topSellSlide/top3.png",
                "./img/menwatch/3.png",
                "./img/menwatch/3_side.png"
            ],
            "topShow": true,
            "description": "Designed for diving enthusiasts, this watch combines durability with elegant design."
        },
        {
            "product_id": "R004",
            "name": "Rado True Thinline",
            "watch_type": "Quartz",
            "price": 1400.00,
            "discount": 5,
            "gender": "men",
            "company": "Rado",
            "rating": "4.1",
            "numRatings": "1100",
            "isNew": false,
            "image_url": "./img/menwatch/top4.png",
            "sideImg_url": "./img/menwatch/top4-1.png",
            "images": [
                "./img/topSellSlide/top4.png",
                "./img/menwatch/4.png",
                "./img/menwatch/4_side.png"
            ],
            "topShow": true,
            "description": "A slim and lightweight quartz watch ideal for those who value minimalistic design."
        },
        {
            "product_id": "R005",
            "name": "Rado DiaMaster",
            "watch_type": "Automatic",
            "price": 1800.00,
            "discount": 12,
            "gender": "men",
            "company": "Rado",
            "rating": "4.4",
            "numRatings": "900",
            "isNew": true,
            "image_url": "./img/menwatch/top5.png",
            "sideImg_url": "./img/menwatch/top5-1.png",
            "images": [
                "./img/topSellSlide/top5.png",
                "./img/menwatch/5.png",
                "./img/menwatch/5_side.png"
            ],
            "topShow": true,
            "description": "An elegant automatic watch with a durable build, designed for modern men."
        },
        {
            "product_id": "R006",
            "name": "Rado True Thinline Xl",
            "watch_type": "Quartz",
            "price": 1300.00,
            "discount": 10,
            "gender": "women",
            "company": "Rado",
            "rating": "4.3",
            "numRatings": "600",
            "isNew": false,
            "image_url": "./img/menwatch/top5.png",
            "sideImg_url": "./img/menwatch/top5-1.png",
            "images": [
                "./img/topSellSlide/top6.png",
                "./img/women/6.png",
                "./img/women/6_side.png"
            ],
            "topShow": false,
            "description": "A refined quartz watch with an extra-large design for those who appreciate bold style."
        },
        {
            "product_id": "R007",
            "name": "Rado Florence",
            "watch_type": "Automatic",
            "price": 1100.00,
            "discount": 20,
            "gender": "women",
            "company": "Rado",
            "rating": "4.6",
            "numRatings": "300",
            "isNew": true,
            "image_url": "./img/women/9.png",
            "sideImg_url": "./img/women/17.png",
            "images": [
                "./img/topSellSlide/top7.png",
                "./img/women/7.png",
                "./img/women/7_side.png"
            ],
            "topShow": false,
            "description": "A stylish automatic watch designed for women who appreciate elegance and craftsmanship."
        },
        {
            "product_id": "R008",
            "name": "Rado True Diamonds",
            "watch_type": "Quartz",
            "price": 1700.00,
            "discount": 15,
            "gender": "women",
            "company": "Rado",
            "rating": "4.8",
            "numRatings": "400",
            "isNew": false,
            "image_url": "./img/women/9.png",
            "sideImg_url": "./img/women/18.png",
            "images": [
                "./img/topSellSlide/top8.png",
                "./img/women/8.png",
                "./img/women/8_side.png"
            ],
            "topShow": false,
            "description": "A luxurious quartz watch adorned with diamonds, perfect for special occasions."
        },
        {
            "product_id": "R009",
            "name": "Rado HyperChrome Ladies",
            "watch_type": "Automatic",
            "price": 2100.00,
            "discount": 10,
            "gender": "women",
            "company": "Rado",
            "rating": "4.5",
            "numRatings": "700",
            "isNew": true,
            "image_url": "./img/women/9.png",
            "sideImg_url": "./img/women/19.png",
            "images": [
                "./img/women/Rado_HyperChrome_Ladies.jpg",
                "./img/women/9.png",
                "./img/women/9_side.png"
            ],
            "topShow": false,
            "description": "A sophisticated automatic watch with a bold design, perfect for the modern woman."
        },
        {
            "product_id": "R010",
            "name": "Rado Centrix Ladies",
            "watch_type": "Quartz",
            "price": 1200.00,
            "discount": 5,
            "gender": "women",
            "company": "Rado",
            "rating": "4.0",
            "numRatings": "500",
            "isNew": false,
            "image_url": "./img/women/9.png",
            "sideImg_url": "./img/women/20.png",
            "images": [
                "./img/women/Rado_Centrix_Ladies.jpg",
                "./img/women/10.png",
                "./img/women/10_side.png"
            ],
            "topShow": false,
            "description": "A delicate quartz watch offering a classic look and reliable performance."
        },
        {
            "product_id": "C001",
            "name": "Citizen Eco-Drive Chronograph",
            "watch_type": "Chronograph",
            "price": 600.00,
            "discount": 10,
            "gender": "men",
            "company": "Citizen",
            "rating": "4.3",
            "numRatings": "1800",
            "isNew": false,
            "image_url": "./img/menwatch/top6.png",
            "sideImg_url": "./img/menwatch/top6-1.png",
            "images": [
                "./img/men/Citizen_Eco-Drive_Chronograph.jpg",
                "./img/men/Citizen_Eco-Drive_Chronograph_side.jpg",
                "./img/men/Citizen_Eco-Drive_Chronograph_3.jpg"
            ],
            "topShow": true,
            "description": "The Citizen Eco-Drive Chronograph combines precision timing with a sleek design and eco-friendly technology."
        },
        {
            "product_id": "C002",
            "name": "Citizen Promaster Diver",
            "watch_type": "Diver",
            "price": 800.00,
            "discount": 15,
            "gender": "men",
            "company": "Citizen",
            "rating": "4.7",
            "numRatings": "2200",
            "isNew": true,
            "image_url": "./img/menwatch/top7.png",
            "sideImg_url": "./img/menwatch/top7-1.png",
            "images": [
                "./img/men/Citizen_Promaster_Diver.jpg",
                "./img/men/Citizen_Promaster_Diver_side.jpg",
                "./img/men/Citizen_Promaster_Diver_3.jpg"
            ],
            "topShow": true,
            "description": "The Citizen Promaster Diver is designed for underwater adventures with advanced features and durability."
        },
        {
            "product_id": "C003",
            "name": "Citizen Quartz Classic",
            "watch_type": "Quartz",
            "price": 300.00,
            "discount": 5,
            "gender": "men",
            "company": "Citizen",
            "rating": "4.0",
            "numRatings": "1500",
            "isNew": false,
            "image_url": "./img/menwatch/top8.png",
            "sideImg_url": "./img/menwatch/top8-1.png",
            "images": [
                "./img/men/Citizen_Quartz_Classic.jpg",
                "./img/men/Citizen_Quartz_Classic_side.jpg",
                "./img/men/Citizen_Quartz_Classic_3.jpg"
            ],
            "topShow": true,
            "description": "The Citizen Quartz Classic offers a timeless design with reliable quartz movement, perfect for everyday wear."
        },
        {
            "product_id": "C004",
            "name": "Citizen Eco-Drive Satellite Wave",
            "watch_type": "Satellite",
            "price": 1200.00,
            "discount": 20,
            "gender": "men",
            "company": "Citizen",
            "rating": "4.8",
            "numRatings": "900",
            "isNew": true,
            "image_url": "./img/men/Citizen_Eco-Drive_Satellite_Wave.jpg",
            "sideImg_url": "./img/men/Citizen_Eco-Drive_Satellite_Wave_side.jpg",
            "images": [
                "./img/men/Citizen_Eco-Drive_Satellite_Wave.jpg",
                "./img/men/Citizen_Eco-Drive_Satellite_Wave_side.jpg",
                "./img/men/Citizen_Eco-Drive_Satellite_Wave_3.jpg"
            ],
            "topShow": false,
            "description": "The Citizen Eco-Drive Satellite Wave features advanced satellite timekeeping technology and a sophisticated design."
        },
        {
            "product_id": "C005",
            "name": "Citizen Aqualand",
            "watch_type": "Diver",
            "price": 900.00,
            "discount": 10,
            "gender": "men",
            "company": "Citizen",
            "rating": "4.4",
            "numRatings": "1200",
            "isNew": false,
            "image_url": "./img/men/Citizen_Aqualand.jpg",
            "sideImg_url": "./img/men/Citizen_Aqualand_side.jpg",
            "images": [
                "./img/men/Citizen_Aqualand.jpg",
                "./img/men/Citizen_Aqualand_side.jpg",
                "./img/men/Citizen_Aqualand_3.jpg"
            ],
            "topShow": false,
            "description": "The Citizen Aqualand is designed for deep-sea diving with robust features and a durable build."
        },
        {
            "product_id": "C006",
            "name": "Citizen Eco-Drive Elegant",
            "watch_type": "Quartz",
            "price": 500.00,
            "discount": 15,
            "gender": "women",
            "company": "Citizen",
            "rating": "4.5",
            "numRatings": "1100",
            "isNew": true,
            "image_url": "./img/women/Citizen_Eco-Drive_Elegant.jpg",
            "sideImg_url": "./img/women/Citizen_Eco-Drive_Elegant_side.jpg",
            "images": [
                "./img/women/Citizen_Eco-Drive_Elegant.jpg",
                "./img/women/Citizen_Eco-Drive_Elegant_side.jpg",
                "./img/women/Citizen_Eco-Drive_Elegant_3.jpg"
            ],
            "topShow": false,
            "description": "The Citizen Eco-Drive Elegant combines a refined design with solar-powered technology for a stylish accessory."
        },
        {
            "product_id": "C007",
            "name": "Citizen L Sunrise",
            "watch_type": "Quartz",
            "price": 350.00,
            "discount": 10,
            "gender": "women",
            "company": "Citizen",
            "rating": "4.2",
            "numRatings": "800",
            "isNew": false,
            "image_url": "./img/women/Citizen_L_Sunrise.jpg",
            "sideImg_url": "./img/women/Citizen_L_Sunrise_side.jpg",
            "images": [
                "./img/women/Citizen_L_Sunrise.jpg",
                "./img/women/Citizen_L_Sunrise_side.jpg",
                "./img/women/Citizen_L_Sunrise_3.jpg"
            ],
            "topShow": false,
            "description": "The Citizen L Sunrise offers a delicate design with reliable quartz movement, ideal for everyday elegance."
        },
        {
            "product_id": "C008",
            "name": "Citizen Eco-Drive Silhouette",
            "watch_type": "Quartz",
            "price": 450.00,
            "discount": 5,
            "gender": "women",
            "company": "Citizen",
            "rating": "4.3",
            "numRatings": "950",
            "isNew": true,
            "image_url": "./img/women/Citizen_Eco-Drive_Silhouette.jpg",
            "sideImg_url": "./img/women/Citizen_Eco-Drive_Silhouette_side.jpg",
            "images": [
                "./img/women/Citizen_Eco-Drive_Silhouette.jpg",
                "./img/women/Citizen_Eco-Drive_Silhouette_side.jpg",
                "./img/women/Citizen_Eco-Drive_Silhouette_3.jpg"
            ],
            "topShow": false,
            "description": "The Citizen Eco-Drive Silhouette features a minimalist design with the precision of quartz technology."
        },
        {
            "product_id": "C009",
            "name": "Citizen Eco-Drive Stellar",
            "watch_type": "Quartz",
            "price": 550.00,
            "discount": 20,
            "gender": "women",
            "company": "Citizen",
            "rating": "4.6",
            "numRatings": "1300",
            "isNew": true,
            "image_url": "./img/women/Citizen_Eco-Drive_Stellar.jpg",
            "sideImg_url": "./img/women/Citizen_Eco-Drive_Stellar_side.jpg",
            "images": [
                "./img/women/Citizen_Eco-Drive_Stellar.jpg",
                "./img/women/Citizen_Eco-Drive_Stellar_side.jpg",
                "./img/women/Citizen_Eco-Drive_Stellar_3.jpg"
            ],
            "topShow": false,
            "description": "The Citizen Eco-Drive Stellar offers a stunning design with solar-powered technology for accurate timekeeping."
        },
        {
            "product_id": "C010",
            "name": "Citizen Exceed",
            "watch_type": "Quartz",
            "price": 600.00,
            "discount": 15,
            "gender": "women",
            "company": "Citizen",
            "rating": "4.4",
            "numRatings": "950",
            "isNew": false,
            "image_url": "./img/women/Citizen_Exceed.jpg",
            "sideImg_url": "./img/women/Citizen_Exceed_side.jpg",
            "images": [
                "./img/women/Citizen_Exceed.jpg",
                "./img/women/Citizen_Exceed_side.jpg",
                "./img/women/Citizen_Exceed_3.jpg"
            ],
            "topShow": false,
            "description": "The Citizen Exceed combines sophisticated design with precise quartz movement for a refined timepiece."
        },
        {
            "product_id": "F001",
            "name": "Fossil Grant Chronograph",
            "watch_type": "Chronograph",
            "price": 250.00,
            "discount": 10,
            "gender": "men",
            "company": "Fossil",
            "rating": "4.2",
            "numRatings": "1300",
            "isNew": false,
            "image_url": "./img/men/Fossil_Grant_Chronograph.jpg",
            "sideImg_url": "./img/men/Fossil_Grant_Chronograph_side.jpg",
            "images": [
                "./img/men/Fossil_Grant_Chronograph.jpg",
                "./img/men/Fossil_Grant_Chronograph_side.jpg",
                "./img/men/Fossil_Grant_Chronograph_3.jpg"
            ],
            "topShow": false,
            "description": "The Fossil Grant Chronograph features a classic design with precise chronograph functionality for modern men."
        },
        {
            "product_id": "F002",
            "name": "Fossil Gen 5 Smartwatch",
            "watch_type": "Smartwatch",
            "price": 300.00,
            "discount": 5,
            "gender": "men",
            "company": "Fossil",
            "rating": "4.5",
            "numRatings": "2000",
            "isNew": true,
            "image_url": "./img/men/Fossil_Gen_5_Smartwatch.jpg",
            "sideImg_url": "./img/men/Fossil_Gen_5_Smartwatch_side.jpg",
            "images": [
                "./img/men/Fossil_Gen_5_Smartwatch.jpg",
                "./img/men/Fossil_Gen_5_Smartwatch_side.jpg",
                "./img/men/Fossil_Gen_5_Smartwatch_3.jpg"
            ],
            "topShow": false,
            "description": "The Fossil Gen 5 Smartwatch offers advanced features with a sleek design, perfect for tech-savvy men."
        },
        {
            "product_id": "F003",
            "name": "Fossil Machine",
            "watch_type": "Automatic",
            "price": 180.00,
            "discount": 15,
            "gender": "men",
            "company": "Fossil",
            "rating": "4.1",
            "numRatings": "1000",
            "isNew": false,
            "image_url": "./img/men/Fossil_Machine.jpg",
            "sideImg_url": "./img/men/Fossil_Machine_side.jpg",
            "images": [
                "./img/men/Fossil_Machine.jpg",
                "./img/men/Fossil_Machine_side.jpg",
                "./img/men/Fossil_Machine_3.jpg"
            ],
            "topShow": false,
            "description": "The Fossil Machine is a robust automatic watch with a distinctive design, ideal for enthusiasts."
        },
        {
            "product_id": "F004",
            "name": "Fossil Townsman",
            "watch_type": "Quartz",
            "price": 220.00,
            "discount": 20,
            "gender": "men",
            "company": "Fossil",
            "rating": "4.3",
            "numRatings": "1400",
            "isNew": true,
            "image_url": "./img/men/Fossil_Townsman.jpg",
            "sideImg_url": "./img/men/Fossil_Townsman_side.jpg",
            "images": [
                "./img/men/Fossil_Townsman.jpg",
                "./img/men/Fossil_Townsman_side.jpg",
                "./img/men/Fossil_Townsman_3.jpg"
            ],
            "topShow": false,
            "description": "The Fossil Townsman offers a sophisticated look with reliable quartz movement, perfect for any occasion."
        },
        {
            "product_id": "F005",
            "name": "Fossil Minimalist",
            "watch_type": "Quartz",
            "price": 150.00,
            "discount": 10,
            "gender": "men",
            "company": "Fossil",
            "rating": "4.0",
            "numRatings": "900",
            "isNew": false,
            "image_url": "./img/men/Fossil_Minimalist.jpg",
            "sideImg_url": "./img/men/Fossil_Minimalist_side.jpg",
            "images": [
                "./img/men/Fossil_Minimalist.jpg",
                "./img/men/Fossil_Minimalist_side.jpg",
                "./img/men/Fossil_Minimalist_3.jpg"
            ],
            "topShow": false,
            "description": "The Fossil Minimalist delivers a sleek and clean design with dependable quartz accuracy."
        },
        {
            "product_id": "F006",
            "name": "Fossil Jacqueline",
            "watch_type": "Quartz",
            "price": 180.00,
            "discount": 15,
            "gender": "women",
            "company": "Fossil",
            "rating": "4.4",
            "numRatings": "1100",
            "isNew": true,
            "image_url": "./img/women/Fossil_Jacqueline.jpg",
            "sideImg_url": "./img/women/Fossil_Jacqueline_side.jpg",
            "images": [
                "./img/women/Fossil_Jacqueline.jpg",
                "./img/women/Fossil_Jacqueline_side.jpg",
                "./img/women/Fossil_Jacqueline_3.jpg"
            ],
            "topShow": false,
            "description": "The Fossil Jacqueline combines elegance with quartz precision, designed for the modern woman."
        },
        {
            "product_id": "F007",
            "name": "Fossil Q Venture HR",
            "watch_type": "Smartwatch",
            "price": 300.00,
            "discount": 5,
            "gender": "women",
            "company": "Fossil",
            "rating": "4.6",
            "numRatings": "1500",
            "isNew": true,
            "image_url": "./img/women/Fossil_Q_Venture_HR.jpg",
            "sideImg_url": "./img/women/Fossil_Q_Venture_HR_side.jpg",
            "images": [
                "./img/women/Fossil_Q_Venture_HR.jpg",
                "./img/women/Fossil_Q_Venture_HR_side.jpg",
                "./img/women/Fossil_Q_Venture_HR_3.jpg"
            ],
            "topShow": false,
            "description": "The Fossil Q Venture HR smartwatch offers cutting-edge features with a fashionable design, tailored for women."
        },
        {
            "product_id": "F008",
            "name": "Fossil Riley Multifunction",
            "watch_type": "Multifunction",
            "price": 200.00,
            "discount": 20,
            "gender": "women",
            "company": "Fossil",
            "rating": "4.3",
            "numRatings": "950",
            "isNew": false,
            "image_url": "./img/women/Fossil_Riley_Multifunction.jpg",
            "sideImg_url": "./img/women/Fossil_Riley_Multifunction_side.jpg",
            "images": [
                "./img/women/Fossil_Riley_Multifunction.jpg",
                "./img/women/Fossil_Riley_Multifunction_side.jpg",
                "./img/women/Fossil_Riley_Multifunction_3.jpg"
            ],
            "topShow": false,
            "description": "The Fossil Riley Multifunction watch offers versatile features with a chic design, ideal for everyday wear."
        },
        {
            "product_id": "F009",
            "name": "Fossil Esme",
            "watch_type": "Quartz",
            "price": 170.00,
            "discount": 10,
            "gender": "women",
            "company": "Fossil",
            "rating": "4.2",
            "numRatings": "800",
            "isNew": false,
            "image_url": "./img/women/Fossil_Esme.jpg",
            "sideImg_url": "./img/women/Fossil_Esme_side.jpg",
            "images": [
                "./img/women/Fossil_Esme.jpg",
                "./img/women/Fossil_Esme_side.jpg",
                "./img/women/Fossil_Esme_3.jpg"
            ],
            "topShow": false,
            "description": "The Fossil Esme is a stylish quartz watch with a touch of sophistication, perfect for various occasions."
        },
        {
            "product_id": "F010",
            "name": "Fossil Georgia",
            "watch_type": "Quartz",
            "price": 160.00,
            "discount": 5,
            "gender": "women",
            "company": "Fossil",
            "rating": "4.1",
            "numRatings": "750",
            "isNew": false,
            "image_url": "./img/women/Fossil_Georgia.jpg",
            "sideImg_url": "./img/women/Fossil_Georgia_side.jpg",
            "images": [
                "./img/women/Fossil_Georgia.jpg",
                "./img/women/Fossil_Georgia_side.jpg",
                "./img/women/Fossil_Georgia_3.jpg"
            ],
            "topShow": false,
            "description": "The Fossil Georgia offers a classic look with quartz accuracy, making it a versatile addition to any wardrobe."
        },
        {
            "product_id": "A001",
            "name": "Armani Exchange Chronograph",
            "watch_type": "Chronograph",
            "price": 250.00,
            "discount": 10,
            "gender": "men",
            "company": "Armani Exchange",
            "rating": "4.4",
            "numRatings": "1200",
            "isNew": false,
            "image_url": "./img/men/Armani_Exchange_Chronograph.jpg",
            "sideImg_url": "./img/men/Armani_Exchange_Chronograph_side.jpg",
            "images": [
                "./img/men/Armani_Exchange_Chronograph.jpg",
                "./img/men/Armani_Exchange_Chronograph_side.jpg",
                "./img/men/Armani_Exchange_Chronograph_3.jpg"
            ],
            "topShow": false,
            "description": "The Armani Exchange Chronograph combines a sporty design with precise chronograph functionality, perfect for active men."
        },
        {
            "product_id": "A002",
            "name": "Armani Exchange Diver",
            "watch_type": "Diver",
            "price": 280.00,
            "discount": 15,
            "gender": "men",
            "company": "Armani Exchange",
            "rating": "4.3",
            "numRatings": "1000",
            "isNew": true,
            "image_url": "./img/men/Armani_Exchange_Diver.jpg",
            "sideImg_url": "./img/men/Armani_Exchange_Diver_side.jpg",
            "images": [
                "./img/men/Armani_Exchange_Diver.jpg",
                "./img/men/Armani_Exchange_Diver_side.jpg",
                "./img/men/Armani_Exchange_Diver_3.jpg"
            ],
            "topShow": false,
            "description": "The Armani Exchange Diver offers rugged durability and a classic dive watch design, ideal for underwater adventures."
        },
        {
            "product_id": "A003",
            "name": "Armani Exchange Minimalist",
            "watch_type": "Quartz",
            "price": 180.00,
            "discount": 5,
            "gender": "men",
            "company": "Armani Exchange",
            "rating": "4.1",
            "numRatings": "800",
            "isNew": false,
            "image_url": "./img/men/Armani_Exchange_Minimalist.jpg",
            "sideImg_url": "./img/men/Armani_Exchange_Minimalist_side.jpg",
            "images": [
                "./img/men/Armani_Exchange_Minimalist.jpg",
                "./img/men/Armani_Exchange_Minimalist_side.jpg",
                "./img/men/Armani_Exchange_Minimalist_3.jpg"
            ],
            "topShow": false,
            "description": "The Armani Exchange Minimalist is designed for simplicity and elegance, offering a sleek quartz watch experience."
        },
        {
            "product_id": "A004",
            "name": "Armani Exchange Automatic",
            "watch_type": "Automatic",
            "price": 300.00,
            "discount": 20,
            "gender": "men",
            "company": "Armani Exchange",
            "rating": "4.5",
            "numRatings": "1500",
            "isNew": true,
            "image_url": "./img/men/Armani_Exchange_Automatic.jpg",
            "sideImg_url": "./img/men/Armani_Exchange_Automatic_side.jpg",
            "images": [
                "./img/men/Armani_Exchange_Automatic.jpg",
                "./img/men/Armani_Exchange_Automatic_side.jpg",
                "./img/men/Armani_Exchange_Automatic_3.jpg"
            ],
            "topShow": false,
            "description": "The Armani Exchange Automatic offers sophisticated craftsmanship with an automatic movement, perfect for watch enthusiasts."
        },
        {
            "product_id": "A005",
            "name": "Armani Exchange Smartwatch",
            "watch_type": "Smartwatch",
            "price": 350.00,
            "discount": 10,
            "gender": "men",
            "company": "Armani Exchange",
            "rating": "4.6",
            "numRatings": "2000",
            "isNew": true,
            "image_url": "./img/men/Armani_Exchange_Smartwatch.jpg",
            "sideImg_url": "./img/men/Armani_Exchange_Smartwatch_side.jpg",
            "images": [
                "./img/men/Armani_Exchange_Smartwatch.jpg",
                "./img/men/Armani_Exchange_Smartwatch_side.jpg",
                "./img/men/Armani_Exchange_Smartwatch_3.jpg"
            ],
            "topShow": false,
            "description": "The Armani Exchange Smartwatch combines modern technology with stylish design, featuring advanced smart features."
        },
        {
            "product_id": "A006",
            "name": "Armani Exchange Logo Watch",
            "watch_type": "Quartz",
            "price": 200.00,
            "discount": 15,
            "gender": "women",
            "company": "Armani Exchange",
            "rating": "4.2",
            "numRatings": "900",
            "isNew": false,
            "image_url": "./img/women/Armani_Exchange_Logo_Watch.jpg",
            "sideImg_url": "./img/women/Armani_Exchange_Logo_Watch_side.jpg",
            "images": [
                "./img/women/Armani_Exchange_Logo_Watch.jpg",
                "./img/women/Armani_Exchange_Logo_Watch_side.jpg",
                "./img/women/Armani_Exchange_Logo_Watch_3.jpg"
            ],
            "topShow": false,
            "description": "The Armani Exchange Logo Watch features a bold logo design with reliable quartz movement, perfect for making a statement."
        },
        {
            "product_id": "A007",
            "name": "Armani Exchange Silver Mesh",
            "watch_type": "Quartz",
            "price": 220.00,
            "discount": 10,
            "gender": "women",
            "company": "Armani Exchange",
            "rating": "4.3",
            "numRatings": "950",
            "isNew": true,
            "image_url": "./img/women/Armani_Exchange_Silver_Mesh.jpg",
            "sideImg_url": "./img/women/Armani_Exchange_Silver_Mesh_side.jpg",
            "images": [
                "./img/women/Armani_Exchange_Silver_Mesh.jpg",
                "./img/women/Armani_Exchange_Silver_Mesh_side.jpg",
                "./img/women/Armani_Exchange_Silver_Mesh_3.jpg"
            ],
            "topShow": false,
            "description": "The Armani Exchange Silver Mesh offers a sleek design with a comfortable mesh band and precise quartz movement."
        },
        {
            "product_id": "A008",
            "name": "Armani Exchange Rose Gold",
            "watch_type": "Quartz",
            "price": 250.00,
            "discount": 20,
            "gender": "women",
            "company": "Armani Exchange",
            "rating": "4.4",
            "numRatings": "1100",
            "isNew": true,
            "image_url": "./img/women/Armani_Exchange_Rose_Gold.jpg",
            "sideImg_url": "./img/women/Armani_Exchange_Rose_Gold_side.jpg",
            "images": [
                "./img/women/Armani_Exchange_Rose_Gold.jpg",
                "./img/women/Armani_Exchange_Rose_Gold_side.jpg",
                "./img/women/Armani_Exchange_Rose_Gold_3.jpg"
            ],
            "topShow": false,
            "description": "The Armani Exchange Rose Gold watch features a luxurious rose gold finish with a classic quartz movement."
        },
        {
            "product_id": "A009",
            "name": "Armani Exchange Smartwatch Ladies",
            "watch_type": "Smartwatch",
            "price": 350.00,
            "discount": 5,
            "gender": "women",
            "company": "Armani Exchange",
            "rating": "4.5",
            "numRatings": "1300",
            "isNew": true,
            "image_url": "./img/women/Armani_Exchange_Smartwatch_Ladies.jpg",
            "sideImg_url": "./img/women/Armani_Exchange_Smartwatch_Ladies_side.jpg",
            "images": [
                "./img/women/Armani_Exchange_Smartwatch_Ladies.jpg",
                "./img/women/Armani_Exchange_Smartwatch_Ladies_side.jpg",
                "./img/women/Armani_Exchange_Smartwatch_Ladies_3.jpg"
            ],
            "topShow": false,
            "description": "The Armani Exchange Smartwatch Ladies offers a blend of advanced features with a stylish design tailored for women."
        },
        {
            "product_id": "A010",
            "name": "Armani Exchange Minimalist Rose Gold",
            "watch_type": "Quartz",
            "price": 230.00,
            "discount": 10,
            "gender": "women",
            "company": "Armani Exchange",
            "rating": "4.3",
            "numRatings": "850",
            "isNew": false,
            "image_url": "./img/women/Armani_Exchange_Minimalist_Rose_Gold.jpg",
            "sideImg_url": "./img/women/Armani_Exchange_Minimalist_Rose_Gold_side.jpg",
            "images": [
                "./img/women/Armani_Exchange_Minimalist_Rose_Gold.jpg",
                "./img/women/Armani_Exchange_Minimalist_Rose_Gold_side.jpg",
                "./img/women/Armani_Exchange_Minimalist_Rose_Gold_3.jpg"
            ],
            "topShow": false,
            "description": "The Armani Exchange Minimalist Rose Gold features a refined rose gold design with a minimalist quartz movement for a sophisticated look."
        },
        {
            "product_id": "O001",
            "name": "Omega Seamaster Diver",
            "watch_type": "Diver",
            "price": 4500.00,
            "discount": 10,
            "gender": "men",
            "company": "Omega",
            "rating": "4.8",
            "numRatings": "1800",
            "isNew": false,
            "image_url": "./img/men/Omega_Seamaster_Diver.jpg",
            "sideImg_url": "./img/men/Omega_Seamaster_Diver_side.jpg",
            "images": [
                "./img/men/Omega_Seamaster_Diver.jpg",
                "./img/men/Omega_Seamaster_Diver_side.jpg",
                "./img/men/Omega_Seamaster_Diver_3.jpg"
            ],
            "topShow": false,
            "description": "The Omega Seamaster Diver is renowned for its robust build and exceptional underwater capabilities, designed for the serious diver."
        },
        {
            "product_id": "O002",
            "name": "Omega Speedmaster Professional",
            "watch_type": "Chronograph",
            "price": 5000.00,
            "discount": 5,
            "gender": "men",
            "company": "Omega",
            "rating": "4.7",
            "numRatings": "2000",
            "isNew": true,
            "image_url": "./img/men/Omega_Speedmaster_Professional.jpg",
            "sideImg_url": "./img/men/Omega_Speedmaster_Professional_side.jpg",
            "images": [
                "./img/men/Omega_Speedmaster_Professional.jpg",
                "./img/men/Omega_Speedmaster_Professional_side.jpg",
                "./img/men/Omega_Speedmaster_Professional_3.jpg"
            ],
            "topShow": false,
            "description": "The Omega Speedmaster Professional is celebrated for its precision and history as the first watch on the moon, featuring a classic chronograph design."
        },
        {
            "product_id": "O003",
            "name": "Omega Constellation",
            "watch_type": "Quartz",
            "price": 3500.00,
            "discount": 15,
            "gender": "men",
            "company": "Omega",
            "rating": "4.6",
            "numRatings": "1600",
            "isNew": false,
            "image_url": "./img/men/Omega_Constellation.jpg",
            "sideImg_url": "./img/men/Omega_Constellation_side.jpg",
            "images": [
                "./img/men/Omega_Constellation.jpg",
                "./img/men/Omega_Constellation_side.jpg",
                "./img/men/Omega_Constellation_3.jpg"
            ],
            "topShow": false,
            "description": "The Omega Constellation offers a timeless quartz design with stellar accuracy and a prestigious name."
        },
        {
            "product_id": "O004",
            "name": "Omega De Ville",
            "watch_type": "Automatic",
            "price": 4000.00,
            "discount": 20,
            "gender": "men",
            "company": "Omega",
            "rating": "4.5",
            "numRatings": "1400",
            "isNew": true,
            "image_url": "./img/men/Omega_De_Ville.jpg",
            "sideImg_url": "./img/men/Omega_De_Ville_side.jpg",
            "images": [
                "./img/men/Omega_De_Ville.jpg",
                "./img/men/Omega_De_Ville_side.jpg",
                "./img/men/Omega_De_Ville_3.jpg"
            ],
            "topShow": false,
            "description": "The Omega De Ville is a refined automatic watch with elegant design and exceptional craftsmanship."
        },
        {
            "product_id": "O005",
            "name": "Omega Seamaster Aqua Terra",
            "watch_type": "Automatic",
            "price": 4300.00,
            "discount": 12,
            "gender": "men",
            "company": "Omega",
            "rating": "4.7",
            "numRatings": "1700",
            "isNew": false,
            "image_url": "./img/men/Omega_Seamaster_Aqua_Terra.jpg",
            "sideImg_url": "./img/men/Omega_Seamaster_Aqua_Terra_side.jpg",
            "images": [
                "./img/men/Omega_Seamaster_Aqua_Terra.jpg",
                "./img/men/Omega_Seamaster_Aqua_Terra_side.jpg",
                "./img/men/Omega_Seamaster_Aqua_Terra_3.jpg"
            ],
            "topShow": false,
            "description": "The Omega Seamaster Aqua Terra blends sporty functionality with a sophisticated automatic movement, ideal for both land and sea."
        },
        {
            "product_id": "O006",
            "name": "Omega Constellation Ladies",
            "watch_type": "Quartz",
            "price": 3500.00,
            "discount": 10,
            "gender": "women",
            "company": "Omega",
            "rating": "4.4",
            "numRatings": "1300",
            "isNew": true,
            "image_url": "./img/women/Omega_Constellation_Ladies.jpg",
            "sideImg_url": "./img/women/Omega_Constellation_Ladies_side.jpg",
            "images": [
                "./img/women/Omega_Constellation_Ladies.jpg",
                "./img/women/Omega_Constellation_Ladies_side.jpg",
                "./img/women/Omega_Constellation_Ladies_3.jpg"
            ],
            "topShow": false,
            "description": "The Omega Constellation Ladies is a beautiful quartz watch offering elegance and accuracy with a touch of luxury."
        },
        {
            "product_id": "O007",
            "name": "Omega De Ville Prestige",
            "watch_type": "Quartz",
            "price": 3800.00,
            "discount": 15,
            "gender": "women",
            "company": "Omega",
            "rating": "4.6",
            "numRatings": "1200",
            "isNew": true,
            "image_url": "./img/women/Omega_De_Ville_Prestige.jpg",
            "sideImg_url": "./img/women/Omega_De_Ville_Prestige_side.jpg",
            "images": [
                "./img/women/Omega_De_Ville_Prestige.jpg",
                "./img/women/Omega_De_Ville_Prestige_side.jpg",
                "./img/women/Omega_De_Ville_Prestige_3.jpg"
            ],
            "topShow": false,
            "description": "The Omega De Ville Prestige is a sophisticated quartz watch known for its luxurious design and precision."
        },
        {
            "product_id": "O008",
            "name": "Omega Seamaster Diver 300M",
            "watch_type": "Diver",
            "price": 4500.00,
            "discount": 20,
            "gender": "women",
            "company": "Omega",
            "rating": "4.8",
            "numRatings": "1500",
            "isNew": false,
            "image_url": "./img/women/Omega_Seamaster_Diver_300M.jpg",
            "sideImg_url": "./img/women/Omega_Seamaster_Diver_300M_side.jpg",
            "images": [
                "./img/women/Omega_Seamaster_Diver_300M.jpg",
                "./img/women/Omega_Seamaster_Diver_300M_side.jpg",
                "./img/women/Omega_Seamaster_Diver_300M_3.jpg"
            ],
            "topShow": false,
            "description": "The Omega Seamaster Diver 300M for women offers superior water resistance and a stylish design, perfect for diving and everyday wear."
        },
        {
            "product_id": "O009",
            "name": "Omega Speedmaster Moonwatch",
            "watch_type": "Chronograph",
            "price": 5500.00,
            "discount": 10,
            "gender": "women",
            "company": "Omega",
            "rating": "4.7",
            "numRatings": "1700",
            "isNew": true,
            "image_url": "./img/women/Omega_Speedmaster_Moonwatch.jpg",
            "sideImg_url": "./img/women/Omega_Speedmaster_Moonwatch_side.jpg",
            "images": [
                "./img/women/Omega_Speedmaster_Moonwatch.jpg",
                "./img/women/Omega_Speedmaster_Moonwatch_side.jpg",
                "./img/women/Omega_Speedmaster_Moonwatch_3.jpg"
            ],
            "topShow": false,
            "description": "The Omega Speedmaster Moonwatch is a legendary chronograph known for its space exploration history and elegant design."
        },
        {
            "product_id": "O010",
            "name": "Omega Seamaster Aqua Terra Ladies",
            "watch_type": "Automatic",
            "price": 4300.00,
            "discount": 5,
            "gender": "women",
            "company": "Omega",
            "rating": "4.5",
            "numRatings": "1400",
            "isNew": false,
            "image_url": "./img/women/Omega_Seamaster_Aqua_Terra_Ladies.jpg",
            "sideImg_url": "./img/women/Omega_Seamaster_Aqua_Terra_Ladies_side.jpg",
            "images": [
                "./img/women/Omega_Seamaster_Aqua_Terra_Ladies.jpg",
                "./img/women/Omega_Seamaster_Aqua_Terra_Ladies_side.jpg",
                "./img/women/Omega_Seamaster_Aqua_Terra_Ladies_3.jpg"
            ],
            "topShow": false,
            "description": "The Omega Seamaster Aqua Terra Ladies combines elegant design with automatic precision, perfect for refined tastes."
        }
    ]
}